{
    "code":"v3",
    "languages":[{
        "code":"en",
        "name":"英语",
        "items":[{
            "code":"home_code",
            "name":"home",
            "value":"V3 Home"
        },{
            "code":"welcome_code",
            "name":"welcome",
            "value":"Welcome To V3 Home"
        },{
            "code":"zh_code",
            "name":"zh",
            "value":"V3 Switch Chinese"
        },{
            "code":"en_code",
            "name":"en",
            "value":"V3 Switch English"
        }]
    },{
        "code":"zh",
        "name":"中文",
        "items":[{
            "code":"home_code",
            "name":"home",
            "value":"V3首页"
        },{
            "code":"welcome_code",
            "name":"welcome",
            "value":"欢迎来V3首页"
        },{
            "code":"zh_code",
            "name":"zh",
            "value":"V3切换中文"
        },{
            "code":"en_code",
            "name":"en",
            "value":"V3切换英文"
        }]
    }]
}